{
  "name": "boost-type-index",
  "license": "BSL-1.0",
  "url": "http://boost.org/libs/type_index", 
  "versions": {
    "1.63.0": {
      "url": "git@github.com:boostorg/type_index.git#c52fdfe30c63de43251681a31d0de0bc39116e46", 
      "buck": {
        "url": "https://raw.githubusercontent.com/njlr/type_index/5a493898c86904ebcf6d39073f2407b385729af0/BUCK"
      },
      "dependencies": {
        "boost-config": "1.63.0",
        "boost-static-assert": "1.63.0",
        "boost-type-traits": "1.63.0",
        "boost-mpl": "1.63.0",
        "boost-smart-ptr": "1.63.0",
        "boost-core": "1.63.0",
        "boost-throw-exception": "1.63.0",
        "boost-preprocessor": "1.63.0"
      }
    }
  }
}
